LICENSE
README.md
setup.py
payable_subscriptions.egg-info/PKG-INFO
payable_subscriptions.egg-info/SOURCES.txt
payable_subscriptions.egg-info/dependency_links.txt
payable_subscriptions.egg-info/requires.txt
payable_subscriptions.egg-info/top_level.txt
payablesubs/__init__.py
payablesubs/apps.py
payablesubs/models.py
payablesubs/clients/__init__.py
payablesubs/clients/google.py
payablesubs/clients/venmo.py
payablesubs/management/__init__.py
payablesubs/management/commands/__init__.py
payablesubs/management/commands/_payable_manager.py
payablesubs/management/commands/add_subscription.py
payablesubs/management/commands/print_subscriptions.py
payablesubs/migrations/0001_initial.py
payablesubs/migrations/0002_venmotransaction.py
payablesubs/migrations/0003_payment_delete_venmotransaction.py
payablesubs/migrations/__init__.py
sandbox/__init__.py
sandbox/asgi.py
sandbox/init_db.py
sandbox/manage.py
sandbox/settings.py
sandbox/urls.py
sandbox/wsgi.py