Metadata-Version: 2.1
Name: payable-subscriptions
Version: 1.0.8
Summary: Integrates out-of-the-box payment processing for django-flexible-subscriptions
Home-page: https://github.com/curtis628/payable-subscriptions
Author: Tyler Curtis
Author-email: tjcurt@gmail.com
Project-URL: Source code, https://github.com/curtis628/payable-subscriptions
Project-URL: Issues, https://github.com/curtis628/payable-subscriptions/issues
Classifier: Framework :: Django :: 4.1
Classifier: Intended Audience :: Developers
Classifier: License :: OSI Approved :: GNU General Public License v3 (GPLv3)
Classifier: Operating System :: Unix
Requires-Python: >=3.7
License-File: LICENSE
